spotify_backup/__init__.py
spotify_backup/client.py
spotify_backup-0.0.3.dist-info/entry_points.txt
spotify_backup-0.0.3.dist-info/WHEEL
spotify_backup-0.0.3.dist-info/METADATA
spotify_backup-0.0.3.dist-info/RECORD
