Metadata-Version: 2.1
Name: spotify-backup
Version: 0.0.3
Summary: A Python script that exports all of your Spotify playlists.
Home-page: https://github.com/emkor/spotify-backup
Keywords: spotify,playlist,liked,songs,backup
Author: emkor93
Author-email: emkor93@gmail.com
Requires-Python: >=3.7,<4.0
Classifier: Programming Language :: Python :: 3
Classifier: Programming Language :: Python :: 3.7
Classifier: Programming Language :: Python :: 3.8
Classifier: Programming Language :: Python :: 3.9
Project-URL: Repository, https://github.com/emkor/spotify-backup
